{
  "counters": {
    "session-start": 103,
    "session-end": 0,
    "jump": 842,
    "stuck": 0,
    "unstuck": 0
  },
  "state_counts": {
    "Idle": 623,
    "Meow": 438,
    "Stretch": 403,
    "SitIdle": 592,
    "CleanFace": 343,
    "Sleep": 131,
    "SlowWalk": 631,
    "Walk": 1141,
    "Trot": 683,
    "Run": 663
  },
  "room_counts": {
    "Main Room": 128,
    "Theater + Arcade": 194,
    "Hot Tub": 131,
    "Other": 72
  },
  "session_count": 103,
  "total_jumps": 842,
  "total_stuck_events": 0,
  "favorite_room": "Theater + Arcade",
  "favorite_state": "Walk",
  "last_updated": "2026-02-17T00:36:31.895Z"
}