{
  "counters": {
    "session-start": 62,
    "session-end": 0,
    "jump": 379,
    "stuck": 0,
    "unstuck": 0
  },
  "state_counts": {
    "Idle": 282,
    "Meow": 198,
    "Stretch": 182,
    "SitIdle": 245,
    "CleanFace": 165,
    "Sleep": 56,
    "SlowWalk": 271,
    "Walk": 540,
    "Trot": 310,
    "Run": 290
  },
  "room_counts": {
    "Main Room": 57,
    "Theater + Arcade": 62,
    "Hot Tub": 49,
    "Other": 23
  },
  "session_count": 62,
  "total_jumps": 379,
  "total_stuck_events": 0,
  "favorite_room": "Theater + Arcade",
  "favorite_state": "Walk",
  "last_updated": "2026-02-15T23:27:04.293Z"
}