{
  "counters": {
    "session-start": 106,
    "session-end": 0,
    "jump": 933,
    "stuck": 0,
    "unstuck": 0
  },
  "state_counts": {
    "Idle": 686,
    "Meow": 488,
    "Stretch": 445,
    "SitIdle": 655,
    "CleanFace": 383,
    "Sleep": 140,
    "SlowWalk": 707,
    "Walk": 1272,
    "Trot": 753,
    "Run": 733
  },
  "room_counts": {
    "Main Room": 141,
    "Theater + Arcade": 220,
    "Hot Tub": 146,
    "Other": 78
  },
  "session_count": 106,
  "total_jumps": 933,
  "total_stuck_events": 0,
  "favorite_room": "Theater + Arcade",
  "favorite_state": "Walk",
  "last_updated": "2026-02-17T22:39:55.255Z"
}