{
  "counters": {
    "session-start": 106,
    "session-end": 0,
    "jump": 873,
    "stuck": 0,
    "unstuck": 0
  },
  "state_counts": {
    "Idle": 655,
    "Meow": 467,
    "Stretch": 429,
    "SitIdle": 625,
    "CleanFace": 364,
    "Sleep": 139,
    "SlowWalk": 670,
    "Walk": 1204,
    "Trot": 719,
    "Run": 695
  },
  "room_counts": {
    "Main Room": 134,
    "Theater + Arcade": 203,
    "Hot Tub": 140,
    "Other": 72
  },
  "session_count": 106,
  "total_jumps": 873,
  "total_stuck_events": 0,
  "favorite_room": "Theater + Arcade",
  "favorite_state": "Walk",
  "last_updated": "2026-02-17T21:03:03.279Z"
}