{
  "counters": {
    "session-start": 66,
    "session-end": 0,
    "jump": 422,
    "stuck": 0,
    "unstuck": 0
  },
  "state_counts": {
    "Idle": 319,
    "Meow": 228,
    "Stretch": 200,
    "SitIdle": 272,
    "CleanFace": 172,
    "Sleep": 66,
    "SlowWalk": 298,
    "Walk": 592,
    "Trot": 333,
    "Run": 318
  },
  "room_counts": {
    "Main Room": 62,
    "Theater + Arcade": 72,
    "Hot Tub": 56,
    "Other": 29
  },
  "session_count": 66,
  "total_jumps": 422,
  "total_stuck_events": 0,
  "favorite_room": "Theater + Arcade",
  "favorite_state": "Walk",
  "last_updated": "2026-02-16T00:40:08.241Z"
}