{
  "counters": {
    "session-start": 143,
    "session-end": 0,
    "jump": 1114,
    "stuck": 0,
    "unstuck": 0
  },
  "state_counts": {
    "Idle": 813,
    "Meow": 587,
    "Stretch": 523,
    "SitIdle": 785,
    "CleanFace": 456,
    "Sleep": 191,
    "SlowWalk": 864,
    "Walk": 1538,
    "Trot": 885,
    "Run": 868
  },
  "room_counts": {
    "Main Room": 159,
    "Theater + Arcade": 271,
    "Hot Tub": 187,
    "Other": 90
  },
  "session_count": 143,
  "total_jumps": 1114,
  "total_stuck_events": 0,
  "favorite_room": "Theater + Arcade",
  "favorite_state": "Walk",
  "last_updated": "2026-02-22T23:46:46.982Z"
}