{
  "counters": {
    "room-enter": 1,
    "state_change": 13
  },
  "session_count": 0,
  "favorite_room": "Unknown",
  "favorite_state": "Unknown",
  "room_counts": {},
  "state_counts": {},
  "total_stuck_events": 0,
  "total_jumps": 0,
  "recent_events": [
    {
      "type": "state_change",
      "ts": 1770514843589,
      "time": "2026-02-08T01:40:43.589Z"
    },
    {
      "type": "state_change",
      "ts": 1770514838573,
      "time": "2026-02-08T01:40:38.573Z"
    },
    {
      "type": "state_change",
      "ts": 1770514823597,
      "time": "2026-02-08T01:40:23.597Z"
    },
    {
      "type": "state_change",
      "ts": 1770514818552,
      "time": "2026-02-08T01:40:18.552Z"
    },
    {
      "type": "state_change",
      "ts": 1770514813548,
      "time": "2026-02-08T01:40:13.548Z"
    },
    {
      "type": "state_change",
      "ts": 1770514788522,
      "time": "2026-02-08T01:39:48.522Z"
    },
    {
      "type": "state_change",
      "ts": 1770514778510,
      "time": "2026-02-08T01:39:38.510Z"
    },
    {
      "type": "state_change",
      "ts": 1770514773606,
      "time": "2026-02-08T01:39:33.606Z"
    },
    {
      "type": "state_change",
      "ts": 1770514758483,
      "time": "2026-02-08T01:39:18.483Z"
    },
    {
      "type": "state_change",
      "ts": 1770514743460,
      "time": "2026-02-08T01:39:03.460Z"
    }
  ],
  "last_updated": "2026-02-08T01:46:18.357Z"
}