{
  "counters": {
    "session-start": 46,
    "session-end": 0,
    "jump": 296,
    "stuck": 0,
    "unstuck": 0
  },
  "state_counts": {
    "Idle": 219,
    "Meow": 152,
    "Stretch": 138,
    "SitIdle": 194,
    "CleanFace": 133,
    "Sleep": 36,
    "SlowWalk": 211,
    "Walk": 420,
    "Trot": 247,
    "Run": 221
  },
  "room_counts": {
    "Main Room": 46,
    "Theater + Arcade": 30,
    "Hot Tub": 28,
    "Other": 7
  },
  "session_count": 46,
  "total_jumps": 296,
  "total_stuck_events": 0,
  "favorite_room": "Main Room",
  "favorite_state": "Walk",
  "last_updated": "2026-02-15T04:02:30.296Z"
}